emailhub/__init__.py
emailhub/__version__
emailhub/admin.py
emailhub/apps.py
emailhub/constants.py
emailhub/models.py
emailhub/signals.py
emailhub/urls.py
emailhub/version.py
emailhub/views.py
emailhub/backends/__init__.py
emailhub/backends/console.py
emailhub/backends/dummy.py
emailhub/backends/filebased.py
emailhub/backends/locmem.py
emailhub/backends/smtp.py
emailhub/backends/anymail/__init__.py
emailhub/backends/anymail/console.py
emailhub/backends/anymail/mailgun.py
emailhub/backends/anymail/mailjet.py
emailhub/backends/anymail/mandrill.py
emailhub/backends/anymail/postmark.py
emailhub/backends/anymail/sendgrid.py
emailhub/backends/anymail/sendgrid_v2.py
emailhub/backends/anymail/sendinblue.py
emailhub/backends/anymail/sparkpost.py
emailhub/backends/djcelery_email/__init__.py
emailhub/backends/djcelery_email/celery.py
emailhub/backends/secure_mail/__init__.py
emailhub/backends/secure_mail/console.py
emailhub/backends/secure_mail/filebased.py
emailhub/backends/secure_mail/locmem.py
emailhub/backends/secure_mail/smtp.py
emailhub/conf/__init__.py
emailhub/conf/settings.py
emailhub/locale/fr/LC_MESSAGES/django.mo
emailhub/locale/fr/LC_MESSAGES/django.po
emailhub/management/__init__.py
emailhub/management/commands/__init__.py
emailhub/management/commands/emailhub.py
emailhub/migrations/0001_initial.py
emailhub/migrations/0002_auto_20180531_1801.py
emailhub/migrations/0003_auto_20181107_0744.py
emailhub/migrations/0004_auto_20181206_0655.py
emailhub/migrations/0005_auto_20190827_1441.py
emailhub/migrations/__init__.py
emailhub/runtests/__init__.py
emailhub/runtests/runtests.py
emailhub/runtests/settings.py
emailhub/runtests/urls.py
emailhub/static/emailhub/CodeMirror-contrib/mode/css/css.js
emailhub/static/emailhub/CodeMirror-contrib/mode/htmlmixed/htmlmixed.js
emailhub/static/emailhub/CodeMirror-contrib/mode/xml/xml.js
emailhub/static/emailhub/ckeditor/CHANGES.md
emailhub/static/emailhub/ckeditor/LICENSE.md
emailhub/static/emailhub/ckeditor/README.md
emailhub-0.0.4.dist-info/LICENSE
emailhub-0.0.4.dist-info/METADATA
emailhub-0.0.4.dist-info/WHEEL
emailhub-0.0.4.dist-info/top_level.txt
emailhub-0.0.4.dist-info/zip-safe
emailhub-0.0.4.dist-info/RECORD
